la_headers/__init__.py
la_headers/gen/__init__.py
la_headers/gen/accept/__init__.py
la_headers/gen/accept/brave.py
la_headers/gen/accept/chrome.py
la_headers/gen/accept/firefox.py
la_headers/gen/accept_encondig/__init__.py
la_headers/gen/accept_encondig/brave.py
la_headers/gen/accept_encondig/chrome.py
la_headers/gen/accept_encondig/firefox.py
la_headers/gen/accept_language/__init__.py
la_headers/gen/accept_language/chrome.py
la_headers/gen/accept_language/firefox.py
la_headers/gen/sec_ch_ua/__init__.py
la_headers/gen/sec_ch_ua/brave.py
la_headers/gen/sec_ch_ua/chromie.py
la_headers/gen/sec_ch_ua/firefox.py
la_headers/gen/sec_ch_ua_mobile/__init__.py
la_headers/gen/sec_ch_ua_mobile/brave.py
la_headers/gen/sec_ch_ua_mobile/chromie.py
la_headers/gen/sec_ch_ua_mobile/firefox.py
la_headers/gen/sec_ch_ua_platform/__init__.py
la_headers/gen/sec_ch_ua_platform/brave.py
la_headers/gen/sec_ch_ua_platform/chromie.py
la_headers/gen/sec_ch_ua_platform/firefox.py
la_headers/gen/system/__init__.py
la_headers/gen/system/android.py
la_headers/gen/system/linux.py
la_headers/gen/system/mac.py
la_headers/gen/system/ubuntu.py
la_headers/gen/system/windows.py
la_headers/gen/upgrade_insecure_requests/__init__.py
la_headers/gen/upgrade_insecure_requests/brave.py
la_headers/gen/upgrade_insecure_requests/chrome.py
la_headers/gen/upgrade_insecure_requests/firefox.py
la_headers/gen/upgrade_insecure_requests/safari.py
la_headers/gen/user_agent/__init__.py
la_headers/gen/user_agent/brave.py
la_headers/gen/user_agent/chrome.py
la_headers/gen/user_agent/firefox.py
la_headers/gen/user_agent/safari.py
la_headers/options/__init__.py
la_headers/options/browser/__init__.py
la_headers/options/browser/brave.py
la_headers/options/browser/chrome.py
la_headers/options/browser/firefox.py
la_headers/options/operating_system/__init__.py
la_headers/options/operating_system/android.py
la_headers/options/operating_system/linux.py
la_headers/options/operating_system/mac.py
la_headers-0.0.3.dist-info/WHEEL
la_headers-0.0.3.dist-info/METADATA
la_headers-0.0.3.dist-info/licenses/LICENSE
la_headers-0.0.3.dist-info/RECORD
